minimodulo/__init__.py
minimodulo/minimodulo.py
minimodulo-0.2.dist-info/METADATA
minimodulo-0.2.dist-info/WHEEL
minimodulo-0.2.dist-info/top_level.txt
minimodulo-0.2.dist-info/RECORD
