Metadata-Version: 2.4
Name: minimodulo
Version: 0.2
Summary: Un módulo de ejemplo que solicita datos
Home-page: https://github.com/iortizdeluzu/minimodulo
Author: Iker Ortiz de Luzuriaga
Author-email: iker.ortiz@dipc.org
Classifier: Programming Language :: Python :: 3
Classifier: License :: OSI Approved :: MIT License
Classifier: Operating System :: OS Independent
Requires-Python: >=3.8
Requires-Dist: numpy>=1.23
Requires-Dist: pandas
Requires-Dist: requests
Dynamic: author
Dynamic: author-email
Dynamic: classifier
Dynamic: home-page
Dynamic: requires-dist
Dynamic: requires-python
Dynamic: summary
